tsd_config/__init__.py
tsd_config/config.py
tsd_config/exceptions.py
tsd_config-0.4.0.dist-info/METADATA
tsd_config-0.4.0.dist-info/WHEEL
tsd_config-0.4.0.dist-info/RECORD
